{
  "type": "GROUP",
"name": "Global Information",
"path": "",
"pathFormatted": "group_missing-name-b06d1",
"stats": {
    "name": "Global Information",
    "numberOfRequests": {
        "total": 3000,
        "ok": 2759,
        "ko": 241
    },
    "minResponseTime": {
        "total": 283,
        "ok": 295,
        "ko": 283
    },
    "maxResponseTime": {
        "total": 39374,
        "ok": 39374,
        "ko": 2322
    },
    "meanResponseTime": {
        "total": 7764,
        "ok": 8413,
        "ko": 332
    },
    "standardDeviation": {
        "total": 7653,
        "ok": 7644,
        "ko": 218
    },
    "percentiles1": {
        "total": 5637,
        "ok": 6281,
        "ko": 288
    },
    "percentiles2": {
        "total": 8406,
        "ok": 9608,
        "ko": 289
    },
    "percentiles3": {
        "total": 16519,
        "ok": 17338,
        "ko": 297
    },
    "percentiles4": {
        "total": 30145,
        "ok": 32255,
        "ko": 1455
    },
    "group1": {
    "name": "t < 800 ms",
    "count": 238,
    "percentage": 8
},
    "group2": {
    "name": "800 ms < t < 1200 ms",
    "count": 292,
    "percentage": 10
},
    "group3": {
    "name": "t > 1200 ms",
    "count": 2229,
    "percentage": 74
},
    "group4": {
    "name": "failed",
    "count": 241,
    "percentage": 8
},
    "meanNumberOfRequestsPerSecond": {
        "total": 16.666666666666668,
        "ok": 15.327777777777778,
        "ko": 1.3388888888888888
    }
},
"contents": {
"req_fetch-reward-sc-f83e7": {
        "type": "REQUEST",
        "name": "Fetch reward score by studio score",
"path": "Fetch reward score by studio score",
"pathFormatted": "req_fetch-reward-sc-f83e7",
"stats": {
    "name": "Fetch reward score by studio score",
    "numberOfRequests": {
        "total": 500,
        "ok": 500,
        "ko": 0
    },
    "minResponseTime": {
        "total": 868,
        "ok": 868,
        "ko": 0
    },
    "maxResponseTime": {
        "total": 18707,
        "ok": 18707,
        "ko": 0
    },
    "meanResponseTime": {
        "total": 4221,
        "ok": 4221,
        "ko": 0
    },
    "standardDeviation": {
        "total": 4405,
        "ok": 4405,
        "ko": 0
    },
    "percentiles1": {
        "total": 2562,
        "ok": 2562,
        "ko": 0
    },
    "percentiles2": {
        "total": 4062,
        "ok": 4062,
        "ko": 0
    },
    "percentiles3": {
        "total": 8006,
        "ok": 8006,
        "ko": 0
    },
    "percentiles4": {
        "total": 17708,
        "ok": 17708,
        "ko": 0
    },
    "group1": {
    "name": "t < 800 ms",
    "count": 0,
    "percentage": 0
},
    "group2": {
    "name": "800 ms < t < 1200 ms",
    "count": 191,
    "percentage": 38
},
    "group3": {
    "name": "t > 1200 ms",
    "count": 309,
    "percentage": 62
},
    "group4": {
    "name": "failed",
    "count": 0,
    "percentage": 0
},
    "meanNumberOfRequestsPerSecond": {
        "total": 2.7777777777777777,
        "ok": 2.7777777777777777,
        "ko": 0
    }
}
    },"req_get-studio-deta-682e2": {
        "type": "REQUEST",
        "name": "Get Studio details by Studio Id",
"path": "Get Studio details by Studio Id",
"pathFormatted": "req_get-studio-deta-682e2",
"stats": {
    "name": "Get Studio details by Studio Id",
    "numberOfRequests": {
        "total": 500,
        "ok": 500,
        "ko": 0
    },
    "minResponseTime": {
        "total": 978,
        "ok": 978,
        "ko": 0
    },
    "maxResponseTime": {
        "total": 22507,
        "ok": 22507,
        "ko": 0
    },
    "meanResponseTime": {
        "total": 8022,
        "ok": 8022,
        "ko": 0
    },
    "standardDeviation": {
        "total": 6136,
        "ok": 6136,
        "ko": 0
    },
    "percentiles1": {
        "total": 7074,
        "ok": 7074,
        "ko": 0
    },
    "percentiles2": {
        "total": 8993,
        "ok": 8993,
        "ko": 0
    },
    "percentiles3": {
        "total": 15422,
        "ok": 15422,
        "ko": 0
    },
    "percentiles4": {
        "total": 21532,
        "ok": 21532,
        "ko": 0
    },
    "group1": {
    "name": "t < 800 ms",
    "count": 0,
    "percentage": 0
},
    "group2": {
    "name": "800 ms < t < 1200 ms",
    "count": 22,
    "percentage": 4
},
    "group3": {
    "name": "t > 1200 ms",
    "count": 478,
    "percentage": 96
},
    "group4": {
    "name": "failed",
    "count": 0,
    "percentage": 0
},
    "meanNumberOfRequestsPerSecond": {
        "total": 2.7777777777777777,
        "ok": 2.7777777777777777,
        "ko": 0
    }
}
    },"req_fetch-charter-b-feccd": {
        "type": "REQUEST",
        "name": "Fetch charter by studio Route",
"path": "Fetch charter by studio Route",
"pathFormatted": "req_fetch-charter-b-feccd",
"stats": {
    "name": "Fetch charter by studio Route",
    "numberOfRequests": {
        "total": 500,
        "ok": 496,
        "ko": 4
    },
    "minResponseTime": {
        "total": 285,
        "ok": 589,
        "ko": 285
    },
    "maxResponseTime": {
        "total": 21344,
        "ok": 21344,
        "ko": 289
    },
    "meanResponseTime": {
        "total": 6969,
        "ok": 7023,
        "ko": 287
    },
    "standardDeviation": {
        "total": 5524,
        "ok": 5514,
        "ko": 2
    },
    "percentiles1": {
        "total": 5727,
        "ok": 5751,
        "ko": 287
    },
    "percentiles2": {
        "total": 6888,
        "ok": 6893,
        "ko": 288
    },
    "percentiles3": {
        "total": 13649,
        "ok": 13691,
        "ko": 289
    },
    "percentiles4": {
        "total": 20156,
        "ok": 20159,
        "ko": 289
    },
    "group1": {
    "name": "t < 800 ms",
    "count": 13,
    "percentage": 3
},
    "group2": {
    "name": "800 ms < t < 1200 ms",
    "count": 61,
    "percentage": 12
},
    "group3": {
    "name": "t > 1200 ms",
    "count": 422,
    "percentage": 84
},
    "group4": {
    "name": "failed",
    "count": 4,
    "percentage": 1
},
    "meanNumberOfRequestsPerSecond": {
        "total": 2.7777777777777777,
        "ok": 2.7555555555555555,
        "ko": 0.022222222222222223
    }
}
    },"req_fetch-all-studi-f38b5": {
        "type": "REQUEST",
        "name": "Fetch all Studio Ids and Studio names",
"path": "Fetch all Studio Ids and Studio names",
"pathFormatted": "req_fetch-all-studi-f38b5",
"stats": {
    "name": "Fetch all Studio Ids and Studio names",
    "numberOfRequests": {
        "total": 500,
        "ok": 492,
        "ko": 8
    },
    "minResponseTime": {
        "total": 285,
        "ok": 295,
        "ko": 285
    },
    "maxResponseTime": {
        "total": 19859,
        "ok": 19859,
        "ko": 364
    },
    "meanResponseTime": {
        "total": 7444,
        "ok": 7560,
        "ko": 298
    },
    "standardDeviation": {
        "total": 6859,
        "ok": 6853,
        "ko": 25
    },
    "percentiles1": {
        "total": 5886,
        "ok": 6053,
        "ko": 289
    },
    "percentiles2": {
        "total": 7646,
        "ok": 7660,
        "ko": 290
    },
    "percentiles3": {
        "total": 18163,
        "ok": 18169,
        "ko": 298
    },
    "percentiles4": {
        "total": 19815,
        "ok": 19815,
        "ko": 359
    },
    "group1": {
    "name": "t < 800 ms",
    "count": 131,
    "percentage": 26
},
    "group2": {
    "name": "800 ms < t < 1200 ms",
    "count": 2,
    "percentage": 0
},
    "group3": {
    "name": "t > 1200 ms",
    "count": 359,
    "percentage": 72
},
    "group4": {
    "name": "failed",
    "count": 8,
    "percentage": 2
},
    "meanNumberOfRequestsPerSecond": {
        "total": 2.7777777777777777,
        "ok": 2.7333333333333334,
        "ko": 0.044444444444444446
    }
}
    },"req_get-list-of-stu-043da": {
        "type": "REQUEST",
        "name": "Get list of studio summary",
"path": "Get list of studio summary",
"pathFormatted": "req_get-list-of-stu-043da",
"stats": {
    "name": "Get list of studio summary",
    "numberOfRequests": {
        "total": 500,
        "ok": 474,
        "ko": 26
    },
    "minResponseTime": {
        "total": 286,
        "ok": 2990,
        "ko": 286
    },
    "maxResponseTime": {
        "total": 39374,
        "ok": 39374,
        "ko": 1535
    },
    "meanResponseTime": {
        "total": 16970,
        "ok": 17873,
        "ko": 508
    },
    "standardDeviation": {
        "total": 8648,
        "ok": 7950,
        "ko": 408
    },
    "percentiles1": {
        "total": 15314,
        "ok": 15585,
        "ko": 292
    },
    "percentiles2": {
        "total": 18916,
        "ok": 19463,
        "ko": 297
    },
    "percentiles3": {
        "total": 28273,
        "ok": 28429,
        "ko": 1000
    },
    "percentiles4": {
        "total": 36241,
        "ok": 36301,
        "ko": 1533
    },
    "group1": {
    "name": "t < 800 ms",
    "count": 0,
    "percentage": 0
},
    "group2": {
    "name": "800 ms < t < 1200 ms",
    "count": 0,
    "percentage": 0
},
    "group3": {
    "name": "t > 1200 ms",
    "count": 474,
    "percentage": 95
},
    "group4": {
    "name": "failed",
    "count": 26,
    "percentage": 5
},
    "meanNumberOfRequestsPerSecond": {
        "total": 2.7777777777777777,
        "ok": 2.6333333333333333,
        "ko": 0.14444444444444443
    }
}
    },"req_get-monthly-con-6e183": {
        "type": "REQUEST",
        "name": "Get monthly contribution score for particular studio-",
"path": "Get monthly contribution score for particular studio-",
"pathFormatted": "req_get-monthly-con-6e183",
"stats": {
    "name": "Get monthly contribution score for particular studio-",
    "numberOfRequests": {
        "total": 500,
        "ok": 297,
        "ko": 203
    },
    "minResponseTime": {
        "total": 283,
        "ok": 304,
        "ko": 283
    },
    "maxResponseTime": {
        "total": 18765,
        "ok": 18765,
        "ko": 2322
    },
    "meanResponseTime": {
        "total": 2955,
        "ok": 4762,
        "ko": 312
    },
    "standardDeviation": {
        "total": 4553,
        "ok": 5181,
        "ko": 175
    },
    "percentiles1": {
        "total": 325,
        "ok": 2277,
        "ko": 288
    },
    "percentiles2": {
        "total": 1549,
        "ok": 4719,
        "ko": 289
    },
    "percentiles3": {
        "total": 9308,
        "ok": 11455,
        "ko": 294
    },
    "percentiles4": {
        "total": 16948,
        "ok": 17780,
        "ko": 1281
    },
    "group1": {
    "name": "t < 800 ms",
    "count": 94,
    "percentage": 19
},
    "group2": {
    "name": "800 ms < t < 1200 ms",
    "count": 16,
    "percentage": 3
},
    "group3": {
    "name": "t > 1200 ms",
    "count": 187,
    "percentage": 37
},
    "group4": {
    "name": "failed",
    "count": 203,
    "percentage": 41
},
    "meanNumberOfRequestsPerSecond": {
        "total": 2.7777777777777777,
        "ok": 1.65,
        "ko": 1.1277777777777778
    }
}
    }
}

}